thick/__init__.py
thick/py.typed
thick/thick.py
thick-0.0.6.dist-info/LICENSE
thick-0.0.6.dist-info/METADATA
thick-0.0.6.dist-info/WHEEL
thick-0.0.6.dist-info/top_level.txt
thick-0.0.6.dist-info/RECORD
