Metadata-Version: 2.1
Name: thick
Version: 0.0.6
Summary: A Python dictionary that gets Thicker rather than longer
Author-email: Clark Hensley <clarkhensley@duck.com>
Maintainer-email: Clark Hensley <clarkhensley@duck.com>
License: The MIT License (MIT)
Project-URL: Source, https://github.com/ClarkMyWords/thick
License-File: LICENSE
